[
 {
   "track_id": "2cZrrQMjB63c0iIugYH9zS",
   "track_name": "Rain Over Me (feat. Marc Anthony)",
   "duration_ms": 231573
 },
 {
   "track_id": "2iuZJX9X9P0GKaE93xcPjk",
   "track_name": "Sugar",
   "duration_ms": 235493
 },
 {
   "track_id": "39LLxExYz6ewLAcYrzQQyP",
   "track_name": "Levitating",
   "duration_ms": 203807
 },
 {
   "track_id": "2DtPEKs3Pj7E06EoWW4vw8",
   "track_name": "Carnival Of Rust",
   "duration_ms": 262946
 },
 {
   "track_id": "40riOy7x9W7GXjyGp4pjAv",
   "track_name": "Hotel California - 2013 Remaster",
   "duration_ms": 391376
 },
 {
   "track_id": "27tNWlhdAryQY04Gb2ZhUI",
   "track_name": "Roar",
   "duration_ms": 223546
 },
 {
   "track_id": "3Iyq9p4jTQCmPXkzCoG0aI",
   "track_name": "I'll Never Love Again",
   "duration_ms": 166000
 },
 {
   "track_id": "0FE9t6xYkqWXU2ahLh6D8X",
   "track_name": "Shape Of You",
   "duration_ms": 233712
 },
 {
   "track_id": "28sq2vxwsWbDUMByREqpO7",
   "track_name": "Ik Mulaqaat Unplugged",
   "duration_ms": 213661
 },
 {
   "track_id": "6eTPyEkYUmDUFvNxJdNuOD",
   "track_name": "Pani Da Rang Male (From \"Vicky Donor\")",
   "duration_ms": 240786
 },
 {
   "track_id": "0mHyWYXmmCB9iQyK18m3FQ",
   "track_name": "Hello",
   "duration_ms": 251106
 },
 {
   "track_id": "50A1WCxKycJUHRr4Rz6WrD",
   "track_name": "What are Words",
   "duration_ms": 189093
 },
 {
   "track_id": "35ovElsgyAtQwYPYnZJECg",
   "track_name": "Lift Me Up - From Black Panther: Wakanda Forever - Music From and Inspired By"",
   "duration_ms": 196519
 }
]